main.py
utils.py
interfaces/__init__.py
interfaces/auth.py
plugins/__init__.py
plugins/bluesky.py
plugins/mastodon.py
plugins/twitter.py
sbutterfly-2.0.0.dist-info/licenses/LICENSE
sbutterfly-2.0.0.dist-info/METADATA
sbutterfly-2.0.0.dist-info/WHEEL
sbutterfly-2.0.0.dist-info/entry_points.txt
sbutterfly-2.0.0.dist-info/top_level.txt
sbutterfly-2.0.0.dist-info/RECORD
