Metadata-Version: 2.4
Name: sbutterfly
Version: 2.0.0
Summary: Allows you to post to your socials
Requires-Python: >=3.12
License-File: LICENSE
Requires-Dist: atproto>=0.0.61
Requires-Dist: requests>=2.32.3
Dynamic: license-file
